[
  {
    "sources": [
      "propertyfinder",
      "99acres"
    ],
    "area": "Wadi Al Safa 3",
    "property_type": "apartment",
    "layout_type": "standard",
    "quality_tier": "standard",
    "bedrooms": 1,
    "median_price_per_sqft": 1652,
    "listing_count": 7,
    "comparable_count": 7,
    "confidence": "Medium",
    "last_updated": "2026-06-02T05:41:41.407262+00:00",
    "lat": 25.09952163696289,
    "lng": 55.31328582763672,
    "color": "yellow"
  },
  {
    "sources": [
      "bhomes",
      "99acres"
    ],
    "area": "Emirates Hills",
    "property_type": "apartment",
    "layout_type": "standard",
    "quality_tier": "standard",
    "bedrooms": 1,
    "median_price_per_sqft": 1765,
    "listing_count": 9,
    "comparable_count": 9,
    "confidence": "High",
    "last_updated": "2026-06-02T05:41:41.407262+00:00",
    "lat": 25.064877,
    "lng": 55.141668,
    "color": "yellow"
  },
  {
    "sources": [
      "propertyfinder",
      "99acres"
    ],
    "area": "Jabal Ali 1",
    "property_type": "apartment",
    "layout_type": "standard",
    "quality_tier": "standard",
    "bedrooms": 1,
    "median_price_per_sqft": 1769,
    "listing_count": 5,
    "comparable_count": 5,
    "confidence": "Medium",
    "last_updated": "2026-06-02T05:41:41.407262+00:00",
    "lat": 25.029897689819336,
    "lng": 55.13871383666992,
    "color": "yellow"
  },
  {
    "sources": [
      "bhomes",
      "propertyfinder",
      "99acres"
    ],
    "area": "Jumeirah Village Circle",
    "property_type": "apartment",
    "layout_type": "standard",
    "quality_tier": "standard",
    "bedrooms": 1,
    "median_price_per_sqft": 1825,
    "listing_count": 12,
    "comparable_count": 12,
    "confidence": "High",
    "last_updated": "2026-06-02T05:41:41.407262+00:00",
    "lat": 25.056,
    "lng": 55.209,
    "color": "yellow"
  },
  {
    "sources": [
      "bhomes",
      "propertyfinder",
      "99acres"
    ],
    "area": "Dubai Marina",
    "property_type": "apartment",
    "layout_type": "standard",
    "quality_tier": "standard",
    "bedrooms": 1,
    "median_price_per_sqft": 1886,
    "listing_count": 10,
    "comparable_count": 10,
    "confidence": "High",
    "last_updated": "2026-06-02T05:41:41.407262+00:00",
    "lat": 25.068151,
    "lng": 55.129647,
    "color": "yellow"
  },
  {
    "sources": [
      "bhomes",
      "99acres"
    ],
    "area": "Al Hebiah 3",
    "property_type": "apartment",
    "layout_type": "standard",
    "quality_tier": "standard",
    "bedrooms": 1,
    "median_price_per_sqft": 1891,
    "listing_count": 7,
    "comparable_count": 7,
    "confidence": "Medium",
    "last_updated": "2026-06-02T05:41:41.407262+00:00",
    "lat": 25.02453,
    "lng": 55.243196,
    "color": "yellow"
  },
  {
    "sources": [
      "bhomes",
      "propertyfinder",
      "99acres"
    ],
    "area": "Dubai Marina",
    "property_type": "apartment",
    "layout_type": "standard",
    "quality_tier": "standard",
    "bedrooms": 2,
    "median_price_per_sqft": 2038,
    "listing_count": 8,
    "comparable_count": 8,
    "confidence": "High",
    "last_updated": "2026-06-02T05:41:41.407262+00:00",
    "lat": 25.072954,
    "lng": 55.128089,
    "color": "yellow"
  },
  {
    "sources": [
      "bhomes",
      "propertyfinder"
    ],
    "area": "Hadaeq Sheikh Mohammed Bin Rashid",
    "property_type": "apartment",
    "layout_type": "standard",
    "quality_tier": "standard",
    "bedrooms": 1,
    "median_price_per_sqft": 2049,
    "listing_count": 7,
    "comparable_count": 7,
    "confidence": "Medium",
    "last_updated": "2026-06-02T05:41:41.407262+00:00",
    "lat": 25.115477,
    "lng": 55.25108,
    "color": "yellow"
  },
  {
    "sources": [
      "bhomes",
      "propertyfinder",
      "99acres"
    ],
    "area": "Bur Dubai",
    "property_type": "apartment",
    "layout_type": "standard",
    "quality_tier": "standard",
    "bedrooms": 2,
    "median_price_per_sqft": 2368,
    "listing_count": 15,
    "comparable_count": 15,
    "confidence": "High",
    "last_updated": "2026-06-02T05:41:41.407262+00:00",
    "lat": 25.195023,
    "lng": 55.283553,
    "color": "yellow"
  },
  {
    "sources": [
      "bhomes",
      "propertyfinder"
    ],
    "area": "Zabeel",
    "property_type": "apartment",
    "layout_type": "standard",
    "quality_tier": "standard",
    "bedrooms": 1,
    "median_price_per_sqft": 2432,
    "listing_count": 5,
    "comparable_count": 5,
    "confidence": "Medium",
    "last_updated": "2026-06-02T05:41:41.407262+00:00",
    "lat": 25.212088,
    "lng": 55.282761,
    "color": "yellow"
  },
  {
    "sources": [
      "bhomes",
      "propertyfinder"
    ],
    "area": "Bur Dubai",
    "property_type": "apartment",
    "layout_type": "standard",
    "quality_tier": "premium",
    "bedrooms": 1,
    "median_price_per_sqft": 2484,
    "listing_count": 6,
    "comparable_count": 6,
    "confidence": "Medium",
    "last_updated": "2026-06-02T05:41:41.407262+00:00",
    "lat": 25.25863,
    "lng": 55.278074,
    "color": "yellow"
  },
  {
    "sources": [
      "bhomes",
      "propertyfinder",
      "99acres"
    ],
    "area": "Bur Dubai",
    "property_type": "apartment",
    "layout_type": "standard",
    "quality_tier": "standard",
    "bedrooms": 1,
    "median_price_per_sqft": 3132,
    "listing_count": 9,
    "comparable_count": 9,
    "confidence": "High",
    "last_updated": "2026-06-02T05:41:41.407262+00:00",
    "lat": 25.202959,
    "lng": 55.26006,
    "color": "red"
  },
  {
    "sources": [
      "bhomes",
      "propertyfinder"
    ],
    "area": "Palm Jumeirah",
    "property_type": "apartment",
    "layout_type": "standard",
    "quality_tier": "standard",
    "bedrooms": 2,
    "median_price_per_sqft": 3370,
    "listing_count": 6,
    "comparable_count": 6,
    "confidence": "Medium",
    "last_updated": "2026-06-02T05:41:41.407262+00:00",
    "lat": 25.112604,
    "lng": 55.143347,
    "color": "red"
  },
  {
    "sources": [
      "propertyfinder",
      "99acres"
    ],
    "area": "Palm Jumeirah",
    "property_type": "apartment",
    "layout_type": "standard",
    "quality_tier": "standard",
    "bedrooms": 4,
    "median_price_per_sqft": 7437,
    "listing_count": 6,
    "comparable_count": 6,
    "confidence": "Medium",
    "last_updated": "2026-06-02T05:41:41.407262+00:00",
    "lat": 25.123205184936523,
    "lng": 55.11220169067383,
    "color": "red"
  }
]